xgodoglib-0.1.2.dist-info/licenses/LICENSE.txt
xgolib/__init__.py
xgolib/xgolib.py
xgoscreen/LCD_2inch.py
xgoscreen/__init__.py
xgoscreen/lcdconfig.py
xgodoglib-0.1.2.dist-info/METADATA
xgodoglib-0.1.2.dist-info/WHEEL
xgodoglib-0.1.2.dist-info/top_level.txt
xgodoglib-0.1.2.dist-info/RECORD
