Metadata-Version: 2.4
Name: xgodoglib
Version: 0.1.2
Summary: XGO-DOG's python campaign file and graphical display file
Home-page: https://github.com/Xgorobot/XGO-PythonLib
Author: LuwuDynamics
Author-email: hello@xgorobot.com
Classifier: Programming Language :: Python :: 3
Classifier: License :: OSI Approved :: MIT License
Classifier: Operating System :: OS Independent
Requires-Python: >=3.6
License-File: LICENSE.txt
Dynamic: author
Dynamic: author-email
Dynamic: classifier
Dynamic: description
Dynamic: description-content-type
Dynamic: home-page
Dynamic: license-file
Dynamic: requires-python
Dynamic: summary
